nvidia_resiliency_ext/checkpointing/__init__.py
nvidia_resiliency_ext/checkpointing/async_ckpt/cached_metadata_filesystem_reader.py
nvidia_resiliency_ext/checkpointing/async_ckpt/core.py
nvidia_resiliency_ext/checkpointing/async_ckpt/filesystem_async.py
nvidia_resiliency_ext/checkpointing/async_ckpt/state_dict_saver.py
nvidia_resiliency_ext/checkpointing/async_ckpt/torch_ckpt.py
nvidia_resiliency_ext/checkpointing/local/__init__.py
nvidia_resiliency_ext/checkpointing/local/base_state_dict.py
nvidia_resiliency_ext/checkpointing/local/basic_state_dict.py
nvidia_resiliency_ext/checkpointing/local/ckpt_managers/base_manager.py
nvidia_resiliency_ext/checkpointing/local/ckpt_managers/local_manager.py
nvidia_resiliency_ext/checkpointing/local/replication/__init__.py
nvidia_resiliency_ext/checkpointing/local/replication/_torch_future.py
nvidia_resiliency_ext/checkpointing/local/replication/group_utils.py
nvidia_resiliency_ext/checkpointing/local/replication/strategies.py
nvidia_resiliency_ext/checkpointing/local/replication/torch_device_utils.py
nvidia_resiliency_ext/checkpointing/local/replication/utils.py
nvidia_resiliency_ext/checkpointing/utils.py
nvidia_resiliency_ext/fault_tolerance/__init__.py
nvidia_resiliency_ext/fault_tolerance/_ft_rendezvous.py
nvidia_resiliency_ext/fault_tolerance/_torch_elastic_compat/__init__.py
nvidia_resiliency_ext/fault_tolerance/_torch_elastic_compat/agent/__init__.py
nvidia_resiliency_ext/fault_tolerance/_torch_elastic_compat/agent/server/__init__.py
nvidia_resiliency_ext/fault_tolerance/_torch_elastic_compat/agent/server/api.py
nvidia_resiliency_ext/fault_tolerance/_torch_elastic_compat/agent/server/local_elastic_agent.py
nvidia_resiliency_ext/fault_tolerance/_torch_elastic_compat/events/__init__.py
nvidia_resiliency_ext/fault_tolerance/_torch_elastic_compat/events/api.py
nvidia_resiliency_ext/fault_tolerance/_torch_elastic_compat/events/handlers.py
nvidia_resiliency_ext/fault_tolerance/_torch_elastic_compat/metrics/__init__.py
nvidia_resiliency_ext-0.4.1.dist-info/LICENSE.txt
nvidia_resiliency_ext-0.4.1.dist-info/METADATA
nvidia_resiliency_ext-0.4.1.dist-info/WHEEL
nvidia_resiliency_ext-0.4.1.dist-info/entry_points.txt
nvidia_resiliency_ext-0.4.1.dist-info/RECORD
