Metadata-Version: 2.3
Name: nvidia-resiliency-ext
Version: 0.4.1
Summary: NVIDIA Resiliency Package
License: Apache 2.0
Author: NVIDIA Corporation
Requires-Python: >=3.10
Classifier: Development Status :: 4 - Beta
Classifier: License :: Other/Proprietary License
Classifier: Operating System :: OS Independent
Classifier: Programming Language :: Python :: 3
Classifier: Programming Language :: Python :: 3.10
Classifier: Programming Language :: Python :: 3.11
Classifier: Programming Language :: Python :: 3.12
Classifier: Programming Language :: Python :: 3.13
Requires-Dist: defusedxml
Requires-Dist: nvidia-ml-py (>=12.570.86)
Requires-Dist: packaging
Requires-Dist: psutil (>=6.0.0)
Requires-Dist: pynvml (>=12.0.0)
Requires-Dist: pyyaml
Requires-Dist: torch (>=2.3.0)
Project-URL: Repository, https://github.com/NVIDIA/nvidia-resiliency-ext
